<?xml version="1.0" encoding="UTF-8" standalone="yes"?>
<doc-part xmlns="http://map.osm.me/osm-doc-part">
    <feature name="insurance">
        <title lang="ru" key="l10n.feature.insurance.title">Страховая компания</title>
        <title lang="en" key="l10n.feature.insurance.title">Insurance</title>
        <tags>
            <tag>
                <key>office</key>
                <val value="insurance"/>
            </tag>
        </tags>
        <trait>poi</trait>
        <applyed-to>node area</applyed-to>
    </feature>
</doc-part>
